{
  "frame_idx": 899,
  "timestamp": 29.96725126804526,
  "faces": [
    {
      "bbox": [
        758,
        278,
        859,
        400
      ],
      "status": "criminal",
      "name": "yh",
      "person_id": "yh",
      "confidence": 77,
      "color": "red",
      "angle_type": "front",
      "yaw_angle": -0.20794825466562128,
      "bank_type": "base"
    },
    {
      "bbox": [
        213,
        467,
        338,
        650
      ],
      "status": "normal",
      "name": "js",
      "person_id": "js",
      "confidence": 59,
      "color": "green",
      "angle_type": "right_profile",
      "yaw_angle": 79.92081328434394,
      "bank_type": "base"
    }
  ]
}