{
  "frame_idx": 2094,
  "timestamp": 69.80136168552478,
  "faces": [
    {
      "bbox": [
        854,
        337,
        946,
        465
      ],
      "status": "normal",
      "name": "jw",
      "person_id": "jw",
      "confidence": 73,
      "color": "green",
      "angle_type": "right",
      "yaw_angle": 29.39891844152985,
      "bank_type": "base"
    },
    {
      "bbox": [
        261,
        466,
        405,
        624
      ],
      "status": "criminal",
      "name": "yh",
      "person_id": "yh",
      "confidence": 51,
      "color": "red",
      "angle_type": "right",
      "yaw_angle": 16.74916861383825,
      "bank_type": "base"
    }
  ]
}