{
  "frame_idx": 2108,
  "timestamp": 70.26803745610613,
  "faces": [
    {
      "bbox": [
        876,
        338,
        965,
        453
      ],
      "status": "normal",
      "name": "jw",
      "person_id": "jw",
      "confidence": 66,
      "color": "green",
      "angle_type": "front",
      "yaw_angle": -10.515572403722766,
      "bank_type": "base"
    },
    {
      "bbox": [
        502,
        479,
        634,
        646
      ],
      "status": "unknown",
      "name": "Unknown",
      "person_id": null,
      "confidence": 33,
      "color": "yellow",
      "angle_type": "right_profile",
      "yaw_angle": 65.88676821174965,
      "bank_type": null
    }
  ]
}